{"participantes":[{"id":1,"nombre":"Alex","direccion":"Carapungo","telefono":"0979152913","tipo":"Carrera","edad":27,"talla":"Samll","patrocinador":"Independiente"},{"id":2,"nombre":"Ivonne","direccion":"Marianas","telefono":"09479115236","tipo":"Carrera","edad":25,"talla":"Large","patrocinador":"Empresa"},{"id":3,"nombre":"Ernesto","direccion":"Solanda","telefono":"0987812546","tipo":"Ciclismo","edad":35,"talla":"Medium","patrocinador":"Grupo"},{"id":"4","nombre":"Andres","direccion":"Solanda","telefono":"0978234568","tipo":"Duatlon","edad":28,"talla":"Medium","patrocinador":"Grupo"}]}